swagger2markdown.py
swagger2markdown-0.1.10.dist-info/entry_points.txt
swagger2markdown-0.1.10.dist-info/LICENSE
swagger2markdown-0.1.10.dist-info/WHEEL
swagger2markdown-0.1.10.dist-info/METADATA
swagger2markdown-0.1.10.dist-info/RECORD
