Metadata-Version: 2.1
Name: swagger2markdown
Version: 0.1.10
Summary: Converter from Swagger JSON to Markdown.
License: MIT
Author: Constantine Molchanov
Author-email: moigagoo@live.com
Classifier: License :: OSI Approved :: MIT License
Classifier: Programming Language :: Python :: 2
Classifier: Programming Language :: Python :: 2.7
Classifier: Programming Language :: Python :: 3
Classifier: Programming Language :: Python :: 3.4
Classifier: Programming Language :: Python :: 3.5
Classifier: Programming Language :: Python :: 3.6
Classifier: Programming Language :: Python :: 3.7
Requires-Dist: Jinja2 (>=2.10,<3.0)
Requires-Dist: requests (>=2.21,<3.0)
